p3vodafone/TIMESS__.ttf
p3vodafone/__init__.py
p3vodafone/sendmail.py
p3vodafone/srazky.py
p3vodafone/user_interface.py
p3vodafone-2021.2.dist-info/LICENSE
p3vodafone-2021.2.dist-info/METADATA
p3vodafone-2021.2.dist-info/WHEEL
p3vodafone-2021.2.dist-info/entry_points.txt
p3vodafone-2021.2.dist-info/top_level.txt
p3vodafone-2021.2.dist-info/RECORD
