Metadata-Version: 2.1
Name: p3vodafone
Version: 2021.2
Summary: UNKNOWN
Home-page: https://gitlab.com/otevrenamesta/praha3/vyuctovani-vodafone
Author: Štěpán Štrébl
Author-email: strebl.stepan@praha3.cz
License: AGPL-3.0
Platform: UNKNOWN
Requires-Dist: pandas (~=1.2.1)
Requires-Dist: reportlab (~=3.5.59)
Requires-Dist: openpyxl (~=3.0.6)
Requires-Dist: pytk
Requires-Dist: profig
Requires-Dist: appdirs
Requires-Dist: packaging
